fnv1a/__init__.py
fnv1a/__init__.pyi
fnv1a/py.typed
fnv1a-0.2.0.dist-info/LICENSE
fnv1a-0.2.0.dist-info/METADATA
fnv1a-0.2.0.dist-info/WHEEL
fnv1a-0.2.0.dist-info/top_level.txt
fnv1a-0.2.0.dist-info/RECORD
