Metadata-Version: 2.1
Name: fnv1a
Version: 0.2.0
Summary: 64 bit Fnv-1a hash module.
Author-email: plasticuproject <plasticuproject@pm.me>
Project-URL: Homepage, https://github.com/plasticuproject/fnv1a
Keywords: fnv,fnv1a,64 bit,hash
Classifier: Programming Language :: Python :: 3
Classifier: Development Status :: 4 - Beta
Classifier: Intended Audience :: Developers
Classifier: License :: OSI Approved :: MIT License
Classifier: Operating System :: OS Independent
Classifier: Topic :: Utilities
Requires-Python: >=3.11
License-File: LICENSE
